TracHackergotchi-1.2.dist-info/DESCRIPTION.rst
TracHackergotchi-1.2.dist-info/METADATA
TracHackergotchi-1.2.dist-info/RECORD
TracHackergotchi-1.2.dist-info/WHEEL
TracHackergotchi-1.2.dist-info/entry_points.txt
TracHackergotchi-1.2.dist-info/metadata.json
TracHackergotchi-1.2.dist-info/top_level.txt
hackergotchi/__init__.py
hackergotchi/api.py
hackergotchi/identicon.py
hackergotchi/providers.py
hackergotchi/web_ui.py
hackergotchi/htdocs/hackergotchi.css
