Metadata-Version: 2.0
Name: TracHackergotchi
Version: 1.2
Summary: Adds user-specific icons to the Trac timeline view.
Home-page: http://trac-hacks.org/wiki/HackergotchiPlugin
Author: Noah Kantrowitz
Author-email: noah@coderanger.net
License: BSD
Keywords: trac plugin timeline identicon hackergotchi
Platform: UNKNOWN
Classifier: Framework :: Trac
Classifier: Development Status :: 4 - Beta
Classifier: Environment :: Web Environment
Classifier: License :: OSI Approved :: BSD License
Classifier: Natural Language :: English
Classifier: Operating System :: OS Independent
Classifier: Programming Language :: Python
Requires-Dist: Trac
